djangocms_flash/__init__.py
djangocms_flash/cms_plugins.py
djangocms_flash/forms.py
djangocms_flash/models.py
djangocms_flash/locale/af/LC_MESSAGES/django.mo
djangocms_flash/locale/af/LC_MESSAGES/django.po
djangocms_flash/locale/ar/LC_MESSAGES/django.mo
djangocms_flash/locale/ar/LC_MESSAGES/django.po
djangocms_flash/locale/be/LC_MESSAGES/django.mo
djangocms_flash/locale/be/LC_MESSAGES/django.po
djangocms_flash/locale/bg/LC_MESSAGES/django.mo
djangocms_flash/locale/bg/LC_MESSAGES/django.po
djangocms_flash/locale/bn/LC_MESSAGES/django.mo
djangocms_flash/locale/bn/LC_MESSAGES/django.po
djangocms_flash/locale/ca/LC_MESSAGES/django.mo
djangocms_flash/locale/ca/LC_MESSAGES/django.po
djangocms_flash/locale/cmn/LC_MESSAGES/django.mo
djangocms_flash/locale/cmn/LC_MESSAGES/django.po
djangocms_flash/locale/cs/LC_MESSAGES/django.mo
djangocms_flash/locale/cs/LC_MESSAGES/django.po
djangocms_flash/locale/cy/LC_MESSAGES/django.mo
djangocms_flash/locale/cy/LC_MESSAGES/django.po
djangocms_flash/locale/da/LC_MESSAGES/django.mo
djangocms_flash/locale/da/LC_MESSAGES/django.po
djangocms_flash/locale/de/LC_MESSAGES/django.mo
djangocms_flash/locale/de/LC_MESSAGES/django.po
djangocms_flash/locale/el/LC_MESSAGES/django.mo
djangocms_flash/locale/el/LC_MESSAGES/django.po
djangocms_flash/locale/en/LC_MESSAGES/django.mo
djangocms_flash/locale/en/LC_MESSAGES/django.po
djangocms_flash/locale/es/LC_MESSAGES/django.mo
djangocms_flash/locale/es/LC_MESSAGES/django.po
djangocms_flash/locale/es_AR/LC_MESSAGES/django.mo
djangocms_flash/locale/es_AR/LC_MESSAGES/django.po
djangocms_flash/locale/es_BO/LC_MESSAGES/django.mo
djangocms_flash/locale/es_BO/LC_MESSAGES/django.po
djangocms_flash/locale/es_DO/LC_MESSAGES/django.mo
djangocms_flash/locale/es_DO/LC_MESSAGES/django.po
djangocms_flash/locale/et/LC_MESSAGES/django.mo
djangocms_flash/locale/et/LC_MESSAGES/django.po
djangocms_flash/locale/eu/LC_MESSAGES/django.mo
djangocms_flash/locale/eu/LC_MESSAGES/django.po
djangocms_flash-0.3.0.dist-info/DESCRIPTION.rst
djangocms_flash-0.3.0.dist-info/METADATA
djangocms_flash-0.3.0.dist-info/metadata.json
djangocms_flash-0.3.0.dist-info/RECORD
djangocms_flash-0.3.0.dist-info/top_level.txt
djangocms_flash-0.3.0.dist-info/WHEEL
